{"cameraMode":{"drawMode":0,"name":"Shaded","section":"Shading Mode"},"sceneLighting":true,"audioPlay":false,"sceneViewState":{"m_AlwaysRefresh":false,"showFog":true,"showSkybox":true,"showFlares":true,"showImageEffects":true,"showParticleSystems":true,"showVisualEffectGraphs":true,"m_FxEnabled":false},"in2DMode":false,"pivot":{"x":-2.191936731338501,"y":0.8761762380599976,"z":-4.922832012176514},"rotation":{"x":-0.02122638002038002,"y":-0.8990383148193359,"z":0.04509131237864494,"w":-0.43697410821914675},"size":1.998274326324463,"orthographic":false}